Workbook

Sheet Inputs
B1: Northwind Robotics synthetic model, $M unless stated. Synthetic test data.
C3: FY25A | D3: FY26E | E3: FY27E
B4: Revenue growth | D4: 0.04 | E4: 0.035
B5: Gross margin | D5: 0.41 | E5: 0.415
B6: SG&A % of revenue | D6: 0.2 | E6: 0.2
B7: Tax rate | D7: 0.21 | E7: 0.21
B8: D&A | D8: 40 | E8: 42
B9: Dividends | D9: 20 | E9: 21
B10: Capex | D10: 55 | E10: 58

Sheet IS
B1: Income statement ($M)
C3: FY25A | D3: FY26E | E3: FY27E
B5: Revenue | C5: 1600 | D5: =C5*(1+Inputs!D4) | E5: =D5*(1+Inputs!E4)
B6: COGS | C6: 944 | D6: =D5*(1-Inputs!D5) | E6: =E5*Inputs!E5
B7: Gross profit | C7: =C5-C6 | D7: =D5-D6 | E7: =E5-E6
B8: SG&A | C8: 320 | D8: =D5*Inputs!D6 | E8: 350
B9: EBITDA | C9: =C7-C8 | D9: =D7-D8 | E9: =E7-E8
B10: D&A | C10: 38 | D10: =Inputs!D8 | E10: =Inputs!E8
B11: EBIT | C11: =C9-C10 | D11: =D9-D10 | E11: =E9-E10
B12: Tax | C12: 60 | D12: =D11*Inputs!D7 | E12: =E11*Inputs!E7
B13: Net income | C13: =C11-C12 | D13: =D11-D12 | E13: =E11-E12
B15: Memo: FY26 revenue guidance low | D15: =Inputs!#REF!

Sheet BS
B1: Balance sheet ($M)
C3: FY25A | D3: FY26E | E3: FY27E
B4: Assets
B5: Cash | C5: 300 | D5: =CF!D12 | E5: =CF!E12
B6: Accounts receivable | C6: 240 | D6: 260 | E6: 270
B7: PP&E, net | C7: 900 | D7: =C7+Inputs!D10-IS!D10 | E7: =D7+Inputs!E10-IS!E10
B8: Other assets | C8: 1000 | D8: 1012.5 | E8: 1000
B9: Total assets | C9: =SUM(C5:C8) | D9: =SUM(D5:D8) | E9: =SUM(E5:E8)
B11: Debt | C11: 500 | D11: 500 | E11: 500
B12: Common stock | C12: 300 | D12: 300 | E12: 300
B13: Retained earnings | C13: 1640 | D13: =C13+IS!D13-Inputs!D9 | E13: =D13+IS!E13-Inputs!E9
B14: Total liabilities and equity | C14: =SUM(C11:C13) | D14: =SUM(D11:D13) | E14: =SUM(E11:E13)
B15: Check: assets less L&E (should be 0) | C15: =C9-C14 | D15: =D9-D14 | E15: =E9-E14

Sheet CF
B1: Cash flow ($M)
D3: FY26E | E3: FY27E
B5: Net income | D5: =IS!D13 | E5: =IS!E13
B6: D&A | D6: =IS!D10 | E6: =IS!E10
B7: Change in receivables | D7: =-(BS!D6-BS!C6) | E7: =(BS!E6-BS!D6)
B8: Cash from operations | D8: =SUM(D5:D7) | E8: =SUM(E5:E7)
B9: Capex | D9: =-Inputs!D10 | E9: =-Inputs!E10
B10: Dividends | D10: =-Inputs!D9 | E10: =-Inputs!E9
B11: Net change in cash | D11: =D8+D9+D10 | E11: =E8+E9+E10
B12: Ending cash | D12: =BS!C5+D11 | E12: =BS!D5+E11
